setup.py
distributions_kamal/Binomialdistribution.py
distributions_kamal/Gaussiandistribution.py
distributions_kamal/Generaldistribution.py
distributions_kamal/__init__.py
distributions_kamal.egg-info/PKG-INFO
distributions_kamal.egg-info/SOURCES.txt
distributions_kamal.egg-info/dependency_links.txt
distributions_kamal.egg-info/not-zip-safe
distributions_kamal.egg-info/top_level.txt