Metadata-Version: 1.0
Name: distributions-kamal
Version: 0.1
Summary: Gaussian distributions
Home-page: UNKNOWN
Author: Kamal Jain
Author-email: UNKNOWN
License: UNKNOWN
Platform: UNKNOWN
